{
  "notes": [
    {
      "Date": "2020-11-11",
      "timestamp": 1604681050467,
      "author": "blah",
      "criminalId": "9",
      "note": "blah",
      "id": 1
    },
    {
      "Date": "2020-11-11",
      "timestamp": 1604681056997,
      "author": "blah",
      "criminalId": "9",
      "note": "new notes",
      "id": 2
    },
    {
      "Date": "2020-11-11",
      "timestamp": 1604681058349,
      "author": "blah",
      "criminalId": "9",
      "note": "new notes",
      "id": 3
    }
  ],
  "criminals": [
    {}
  ]
}